taskflow/__init__.py
taskflow/core.py
taskflow/parser.py
taskflow/tasks/__init__.py
taskflow/tasks/ai_tasks.py
taskflow/tasks/data_tasks.py
taskflow/tasks/rpa_tasks.py
taskflow_pipeline-0.1.1.dist-info/licenses/LICENSE
taskflow_pipeline-0.1.1.dist-info/METADATA
taskflow_pipeline-0.1.1.dist-info/WHEEL
taskflow_pipeline-0.1.1.dist-info/top_level.txt
taskflow_pipeline-0.1.1.dist-info/RECORD
