Metadata-Version: 2.4
Name: taskflow-pipeline
Version: 0.1.1
Summary: A Python library for orchestrating RPA, data processing, and AI task pipelines from YAML/JSON configurations
Author-email: Berk Terekli <berk.terekli@example.com>
Maintainer-email: Berk Terekli <berk.terekli@example.com>
License: MIT
Project-URL: Homepage, https://github.com/berkterekli/taskflow-pipeline
Project-URL: Repository, https://github.com/berkterekli/taskflow-pipeline
Project-URL: Documentation, https://github.com/berkterekli/taskflow-pipeline#readme
Project-URL: Bug Tracker, https://github.com/berkterekli/taskflow-pipeline/issues
Project-URL: Changelog, https://github.com/berkterekli/taskflow-pipeline/blob/main/CHANGELOG.md
Keywords: automation,rpa,pipeline,workflow,orchestration,task-automation,yaml-config,data-processing,ai-tasks,robotic-process-automation
Classifier: Development Status :: 4 - Beta
Classifier: Intended Audience :: Developers
Classifier: Intended Audience :: System Administrators
Classifier: License :: OSI Approved :: MIT License
Classifier: Operating System :: OS Independent
Classifier: Programming Language :: Python :: 3
Classifier: Programming Language :: Python :: 3.8
Classifier: Programming Language :: Python :: 3.9
Classifier: Programming Language :: Python :: 3.10
Classifier: Programming Language :: Python :: 3.11
Classifier: Programming Language :: Python :: 3.12
Classifier: Topic :: Software Development :: Libraries :: Python Modules
Classifier: Topic :: Office/Business
Classifier: Topic :: System :: Systems Administration
Classifier: Typing :: Typed
Requires-Python: >=3.8
License-File: LICENSE
Requires-Dist: pyyaml>=6.0
Provides-Extra: dev
Requires-Dist: pytest>=7.0; extra == "dev"
Requires-Dist: pytest-cov>=4.0; extra == "dev"
Requires-Dist: black>=23.0; extra == "dev"
Requires-Dist: mypy>=1.0; extra == "dev"
Dynamic: license-file
